{"docs_upgrade_checklist.md":"wsVQPsSv","docs_upgrade_precautions.md":"SnNLB_PA","index.md":"AglDMUmF","posts_02bb9bb8.md":"BsFD3yWo","posts_0315077c.md":"DgV67-bU","posts_064b2b54.md":"DnrOHF_H","posts_0d2b3729.md":"D8doLhzt","posts_10e45a13.md":"CEGqJ1fC","posts_13a4230c.md":"DaZGPulM","posts_1648c8d5.md":"CkhRR9OY","posts_1a7d5d9d.md":"BC0-aNyE","posts_24ba5eaf.md":"h_-_icg8","posts_29dd5873.md":"ChU81tX0","posts_2b43059f.md":"CxWGNDhI","posts_2c22bf13.md":"Di4Bc-Vu","posts_2d22a002.md":"qd0tyQBJ","posts_2dfd8dd9.md":"D84UqQVH","posts_3edbef81.md":"DeRHOsuD","posts_43ac60be.md":"Dks2cj_r","posts_45d6daaf.md":"JJCqe6wi","posts_4822b259.md":"DoawAKoV","posts_49607a7b.md":"B2KkHQvS","posts_4be2011a.md":"DPBeLQEv","posts_51c0725e.md":"D7CGWPsx","posts_55e3861d.md":"CeNLOXPo","posts_569b3671.md":"B1nzlO4s","posts_5b664292.md":"CfXKYQ8x","posts_5d2a427b.md":"k2HMD1bl","posts_6513ad9e.md":"Bjo7NdNU","posts_666539a6.md":"Dbxey0UL","posts_6749a8d7.md":"CF9zbLl6","posts_6c8dde8f.md":"DATQQjDx","posts_7317e374.md":"CcanIdhy","posts_7403161d.md":"BH2XpCwH","posts_74f33be9.md":"D_NMljdf","posts_754dec14.md":"wRwjwaH6","posts_79043038.md":"B3l24NP7","posts_7a78a06b.md":"DO-STZ93","posts_7ec143e2.md":"C1f-SA4q","posts_894a942b.md":"5YT8jYn1","posts_8975db6a.md":"CVcMdNeV","posts_8dfd0529.md":"BCCKNnE8","posts_a7fc9217.md":"B0w1NR64","posts_abab10b0.md":"CZqjNluS","posts_ac8dc62b.md":"CT-YD159","posts_b4178878.md":"CDgLNAyz","posts_b4e5c023.md":"wh5tT-qx","posts_b51fa944.md":"DjkaGzrF","posts_b8d4c961.md":"0CTrFQ5Q","posts_bd53f826.md":"T1-_nUom","posts_bedd4708.md":"0OLVEQU4","posts_bf56f649.md":"DuiI7jPw","posts_c422df2b.md":"B97TFSaJ","posts_d28d16ea.md":"mzQkx-w5","posts_d4e84257.md":"BYY3QxMa","posts_d6bbd820.md":"CucO9cwR","posts_d9b66711.md":"B1uyTPAY","posts_dd1b7a70.md":"BlSJnj--","posts_e5f8c594.md":"BILXZn2b","posts_ed70e259.md":"CtwXpKmM","posts_f92de74b.md":"BB-UWr0S"}
